examples/3 Software interfacing/Abaqus model export/bergsoysund-export.py
examples/3 Software interfacing/Abaqus model export/hardanger-export.py
tests/test_IABSE_step11a.py
tests/test_IABSE_step11c.py
tests/test_IABSE_step2a.py
tests/test_wind.py
wawi/__init__.py
wawi/fe.py
wawi/general.py
wawi/identification.py
wawi/io.py
wawi/modal.py
wawi/plot.py
wawi/prob.py
wawi/random.py
wawi/signal.py
wawi/structural.py
wawi/time_domain.py
wawi/tools.py
wawi/wave.py
wawi/wind.py
wawi/wind_code.py
wawi/ext/__init__.py
wawi/ext/abq.py
wawi/ext/ansys.py
wawi/ext/orcaflex.py
wawi/ext/sofistik.py
wawi/model/__init__.py
wawi/model/_aero.py
wawi/model/_dry.py
wawi/model/_hydro.py
wawi/model/_model.py
wawi/model/_screening.py
wawi-0.0.19.dist-info/licenses/LICENSE
wawi-0.0.19.dist-info/METADATA
wawi-0.0.19.dist-info/WHEEL
wawi-0.0.19.dist-info/top_level.txt
wawi-0.0.19.dist-info/RECORD
