Metadata-Version: 2.4
Name: wawi
Version: 0.0.19
Summary: WAve and WInd response prediction
Author-email: "Knut A. Kvåle" <knut.a.kvale@ntnu.no>, Ole Øiseth <ole.oiseth@ntnu.no>, Aksel Fenerci <aksel.fenerci@ntnu.no>, Øivind Wiig Petersen <oyvind.w.petersen@ntnu.no>
License: MIT License
Project-URL: repository, https://github.com/knutankv/wawi
Project-URL: documentation, https://knutankv.github.io/wawi/
Classifier: License :: OSI Approved :: MIT License
Classifier: Operating System :: OS Independent
Classifier: Programming Language :: Python :: 3
Classifier: Topic :: Scientific/Engineering
Requires-Python: >=3.6
License-File: LICENSE
Requires-Dist: plotly
Requires-Dist: pandas
Requires-Dist: numpy
Requires-Dist: pyvista[jupyter]>=0.38.1
Requires-Dist: scikit-learn
Requires-Dist: trame
Requires-Dist: ipywidgets
Requires-Dist: pyvistaqt
Requires-Dist: beefpy
Dynamic: license-file
